BeanPorter/BeanExtractContext.py
BeanPorter/BeanExtractImporter.py
BeanPorter/__init__.py
BeanPorter/__main__.py
BeanPorter/bean_porter_config.yaml
BeanPorter/bpcml/ASTContext.py
BeanPorter/bpcml/BPCML.py
BeanPorter/bpcml/BuiltinFunctions.py
BeanPorter/bpcml/Decls.py
BeanPorter/bpcml/Exprs.py
BeanPorter/bpcml/Token.py
BeanPorter/bpcml/Tokenizer.py
BeanPorter/bpcml/__init__.py
BeanPorter-0.1.dist-info/LICENSE
BeanPorter-0.1.dist-info/METADATA
BeanPorter-0.1.dist-info/WHEEL
BeanPorter-0.1.dist-info/entry_points.txt
BeanPorter-0.1.dist-info/top_level.txt
BeanPorter-0.1.dist-info/RECORD
