Metadata-Version: 2.1
Name: BeanPorter
Version: 0.1
Summary: Beancount importer
Home-page: https://github.com/WeZZard/BeanPorter
Download-URL: https://github.com/WeZZard/BeanPorter
Author: WeZZard
Author-email: me@wezzard.com
License: MIT
Platform: UNKNOWN
Requires-Python: >=3.6
License-File: LICENSE
Requires-Dist: beancount
Requires-Dist: pyyaml
